[
  {
    "id": 2,
    "title": "Teclado Mecánico Corsair K70 RGB MK.2",
    "description": "Teclado mecánico para juegos con retroiluminación RGB personalizable y switches Cherry MX.",
    "price": "149",
    "code": "TCK70RGBMK2",
    "stock": "25",
    "category": "Teclados",
    "status": true,
    "thumbnails": "https://picsum.photos/seed/picsum/200/300"
  },
  {
    "id": 3,
    "title": "Ratón Logitech G Pro Wireless",
    "description": "Ratón inalámbrico para juegos con sensor HERO 25K y diseño ambidiestro.",
    "price": "129",
    "code": "RLGPROWIRE",
    "stock": "15",
    "category": "Ratones",
    "status": true,
    "thumbnails": "https://picsum.photos/seed/picsum/200/300"
  }
]